cli_client/__init__.py
cli_client/__main__.py
cli_client/client.py
cli_client/config.py
cli_client/exceptions.py
cli_client/models.py
cli_client/utils.py
cli_client-0.1.0.dist-info/LICENSE
cli_client-0.1.0.dist-info/METADATA
cli_client-0.1.0.dist-info/WHEEL
cli_client-0.1.0.dist-info/entry_points.txt
cli_client-0.1.0.dist-info/top_level.txt
cli_client-0.1.0.dist-info/RECORD
