Metadata-Version: 2.2
Name: cli-client
Version: 0.1.0
Summary: CLI клиент для взаимодействия с Model Provider API
Home-page: https://github.com/your_username/cli-client
Author: SensoryLAB
Author-email: SensoryLAB <fox@sensorylab.ru>
Keywords: cli,api,aiohttp,client
Classifier: Programming Language :: Python :: 3
Classifier: License :: OSI Approved :: MIT License
Classifier: Operating System :: OS Independent
Requires-Python: >=3.8
License-File: LICENSE
Requires-Dist: aiohttp>=3.8.1
Provides-Extra: dev
Requires-Dist: pytest>=6.0.0; extra == "dev"
Requires-Dist: pytest-asyncio; extra == "dev"
Dynamic: author
Dynamic: home-page
Dynamic: requires-python
